borca/__init__.py
borca/__main__.py
borca/exceptions/__init__.py
borca/exceptions/exceptions.py
borca/execution/__init__.py
borca/execution/executor.py
borca/orchestrator.py
borca/parsing/__init__.py
borca/parsing/data_format.py
borca/parsing/parser.py
borca/util/__init__.py
borca/util/logging.py
license
borca-2020.5.dist-info/entry_points.txt
borca-2020.5.dist-info/LICENSE
borca-2020.5.dist-info/WHEEL
borca-2020.5.dist-info/METADATA
borca-2020.5.dist-info/RECORD
