Metadata-Version: 2.1
Name: borca
Version: 2020.5
Summary: Lightweight task graph execution defined with pyproject.toml files.
Home-page: https://github.com/AndrewSpittlemeister/borca
License: MIT
Keywords: build tool,task,tasks,make
Author: Andrew Spittlemeister
Author-email: andrew.spittlemeister@gmail.com
Requires-Python: >=3.7,<4.0
Classifier: Environment :: Console
Classifier: License :: OSI Approved :: MIT License
Classifier: Operating System :: OS Independent
Classifier: Programming Language :: Python :: 3
Classifier: Programming Language :: Python :: 3.7
Classifier: Programming Language :: Python :: 3.8
Classifier: Topic :: Software Development :: Build Tools
Requires-Dist: pydantic (>=1.1.1,<2.0.0)
Requires-Dist: toml (>=0.10.0,<0.11.0)
Project-URL: Repository, https://github.com/AndrewSpittlemeister/borca
